{
    "eventTime": "2025-04-07T00:16:30.657113",
    "eventType": "START",
    "inputs": [],
    "job": {
        "facets": {
            "sourceCodeLocation": {
                "_producer": "https://github.com/OpenLineage/OpenLineage/tree/1.29.0/client/python",
                "_schemaURL": "https://raw.githubusercontent.com/OpenLineage/OpenLineage/main/spec/OpenLineage.json#/definitions/SourceCodeLocationJobFacet",
                "type": "python",
                "url": "c:\\lopu-kg-test\\project\\src\\main\\etl_test.py"
            },
            "sql": {
                "_producer": "https://github.com/OpenLineage/OpenLineage/tree/1.29.0/client/python",
                "_schemaURL": "https://raw.githubusercontent.com/OpenLineage/OpenLineage/main/spec/OpenLineage.json#/definitions/SqlJobFacet",
                "query": "\nINSERT INTO wh_Db.BatchDate (batchdate, batchid)\nSELECT\n    '2011-01-01'::DATE,\n    7 batchid\n;\n"
            }
        },
        "name": "load_BatchDate",
        "namespace": "TPC-DI: duckdb-etl"
    },
    "outputs": [],
    "producer": "HARDCODED FOR NOW",
    "run": {
        "facets": {
            "nominalTime": {
                "_producer": "https://github.com/OpenLineage/OpenLineage/tree/1.29.0/client/python",
                "_schemaURL": "https://raw.githubusercontent.com/OpenLineage/OpenLineage/main/spec/OpenLineage.json#/definitions/NominalTimeRunFacet",
                "nominalStartTime": "2025-04-07T00:16:30.657113"
            }
        },
        "runId": "d77e3738-2189-435c-b4dd-072b1bf9c6c5"
    },
    "schemaURL": "https://openlineage.io/spec/1-0-5/OpenLineage.json#/definitions/RunEvent"
}